datatune/__init__.py
datatune/api.py
datatune/config.py
datatune/constants.py
datatune/credentials.py
datatune/dataset.py
datatune/entity.py
datatune/exceptions.py
datatune/extra_column.py
datatune/streaming.py
datatune/view.py
datatune/workspace.py
datatune_client-0.0.2.dist-info/METADATA
datatune_client-0.0.2.dist-info/WHEEL
datatune_client-0.0.2.dist-info/top_level.txt
datatune_client-0.0.2.dist-info/RECORD
